odoo/addons/web_domain_field/README.rst
odoo/addons/web_domain_field/__init__.py
odoo/addons/web_domain_field/__manifest__.py
odoo/addons/web_domain_field/i18n/de.po
odoo/addons/web_domain_field/i18n/fr.po
odoo/addons/web_domain_field/i18n/pt_BR.po
odoo/addons/web_domain_field/i18n/tr.po
odoo/addons/web_domain_field/i18n/web_domain_field.pot
odoo/addons/web_domain_field/readme/CONTRIBUTORS.rst
odoo/addons/web_domain_field/readme/DESCRIPTION.rst
odoo/addons/web_domain_field/readme/USAGE.rst
odoo/addons/web_domain_field/static/description/icon.png
odoo/addons/web_domain_field/static/description/index.html
odoo/addons/web_domain_field/static/src/js/pyeval.js
odoo/addons/web_domain_field/views/web_domain_field.xml
odoo12_addon_web_domain_field-12.0.1.0.0.99.dev13.dist-info/METADATA
odoo12_addon_web_domain_field-12.0.1.0.0.99.dev13.dist-info/WHEEL
odoo12_addon_web_domain_field-12.0.1.0.0.99.dev13.dist-info/top_level.txt
odoo12_addon_web_domain_field-12.0.1.0.0.99.dev13.dist-info/RECORD
